alphabetic_number/__init__.py
alphabetic_number/alphabetic_number.py
alphabetic_number/tests.py
alphabetic_number-0.0.6.dist-info/LICENSE
alphabetic_number-0.0.6.dist-info/METADATA
alphabetic_number-0.0.6.dist-info/WHEEL
alphabetic_number-0.0.6.dist-info/top_level.txt
alphabetic_number-0.0.6.dist-info/RECORD
